sharepay/__init__.py
sharepay/balance.py
sharepay/currency.py
sharepay/debt.py
sharepay/payment.py
sharepay/rate.py
sharepay/sharepay.py
sharepay/transaction.py
sharepay/utils.py
sharepay-0.3.0.dist-info/METADATA
sharepay-0.3.0.dist-info/WHEEL
sharepay-0.3.0.dist-info/licenses/LICENSE
sharepay-0.3.0.dist-info/RECORD
