Metadata-Version: 2.4
Name: sharepay
Version: 0.3.0
Author-email: narumi <toucans-cutouts0f@icloud.com>
License-File: LICENSE
Requires-Python: >=3.11
Requires-Dist: click>=8.1.7
Requires-Dist: httpx>=0.27.2
Requires-Dist: loguru>=0.7.2
Requires-Dist: pandas>=2.2.3
Requires-Dist: pydantic>=2.9.2
